deepcon/__init__.py
deepcon/deepconcovariance.py
deepcon/rundeepcon.py
deepcon/weights-rdd-covariance.hdf5
deepcon-0.4.0.dist-info/LICENSE.txt
deepcon-0.4.0.dist-info/METADATA
deepcon-0.4.0.dist-info/WHEEL
deepcon-0.4.0.dist-info/top_level.txt
deepcon-0.4.0.dist-info/RECORD
