Metadata-Version: 2.1
Name: deepcon
Version: 0.4.0
Summary: Protein Contact Prediction using Dilated Convolutional Neural Networks with Dropout
Home-page: https://github.com/ba-lab/deepcon-package
Author: Badri Adhikari
Author-email: adhikarib@umsl.edu
License: UNKNOWN
Platform: UNKNOWN
Classifier: Programming Language :: Python
Classifier: License :: OSI Approved :: MIT License
Classifier: Intended Audience :: Science/Research
Classifier: Operating System :: OS Independent
Requires-Dist: numpy
Requires-Dist: pyYAML
Requires-Dist: tensorflow
Requires-Dist: keras
